{
  "title": "[REPLACE_CLIENT_NAME] Data Injector",
  "tasks": {
    "data_injector": {
      "name": "data_injector",
      "input": {
        "script": "// ============================================================\n// Workflow JavaScript Action — Hourly BizEvents Demo Injector\n// ============================================================\n// HOW TO USE\n//   1. Find every [REPLACE_...] token and substitute your values.\n//   2. Adjust TUNABLES to match expected production volumes.\n//   3. Extend / remove event generators (sections 1–5) to match\n//      the customer's actual business processes.\n//   4. Import this workflow into Dynatrace Automations.\n//      The workflow runs every 60 minutes using integrated auth.\n//\n// TOKEN REFERENCE\n//   [REPLACE_CLIENT_NAME]       e.g. \"Acme Corp\"\n//   [REPLACE_EVENT_PROVIDER]    e.g. \"acme.event.provider\"\n//   [REPLACE_REGION_1..N]       Production region names\n//   [REPLACE_LOCATION_1..N]     City / data-centre names\n//   [REPLACE_PRODUCT_1..N]      Core product / service names\n//   [REPLACE_CHANNEL_1..N]      Customer-facing channels\n//   [REPLACE_SEGMENT_1..N]      Customer or account segments\n//\n// DIURNAL TRAFFIC MODEL (built-in)\n//   Volume scales by UTC hour to avoid flat \"robot\" charts.\n//   Adjust TIMEZONE_OFFSET_HOURS to shift peak to local business hours.\n//   Weekend dampening is applied automatically (0 = Sunday).\n\nexport default async function () {\n\n  // ─── TUNABLES ────────────────────────────────────────────────────────────\n  const HOURS_WINDOW   = 1;    // window covered per run (keep at 1)\n  const CHUNK          = 500;  // events per ingest request (keep ≤ 500)\n\n  // Peak-hour volumes (diurnal model scales these down during off-hours)\n  const TXN_MIN        = 600;   // [REPLACE] primary transaction floor\n  const TXN_MAX        = 1000;  // [REPLACE] primary transaction ceiling\n  const ORDER_MIN      = 50;    // [REPLACE] secondary event floor\n  const ORDER_MAX      = 150;   // [REPLACE] secondary event ceiling\n  const ALERT_MIN      = 5;     // [REPLACE] platform alert floor\n  const ALERT_MAX      = 15;    // [REPLACE] platform alert ceiling\n  const ERROR_RATE     = 0.02;  // [REPLACE] system error fraction (0.0–1.0)\n  const DECLINE_RATE   = 0.03;  // [REPLACE] business decline/reject fraction\n\n  // Shift peak to local business hours. UTC offset of customer HQ:\n  //   London = 0 (summer) / -1 (winter), US Eastern = -5/-4, APAC SGT = +8\n  const TIMEZONE_OFFSET_HOURS = 0; // [REPLACE]\n\n  // ─── IDENTITY ────────────────────────────────────────────────────────────\n  const CLIENT_NAME    = \"[REPLACE_CLIENT_NAME]\";\n  const EVENT_PROVIDER = \"[REPLACE_EVENT_PROVIDER]\";\n\n  // ─── ENVIRONMENTS ────────────────────────────────────────────────────────\n  // Add/remove rows to match the customer's production footprint.\n  const ENVIRONMENTS = [\n    { name: \"[REPLACE_REGION_1]\", location: \"[REPLACE_LOCATION_1]\", lat: 0.0, lon: 0.0 },\n    { name: \"[REPLACE_REGION_2]\", location: \"[REPLACE_LOCATION_2]\", lat: 0.0, lon: 0.0 },\n  ];\n  // Relative traffic weight per environment (must match ENVIRONMENTS length)\n  const ENV_WEIGHTS = [0.60, 0.40];\n\n  // ─── DIMENSIONS ──────────────────────────────────────────────────────────\n  const PRODUCTS    = [\"[REPLACE_PRODUCT_1]\", \"[REPLACE_PRODUCT_2]\", \"[REPLACE_PRODUCT_3]\"];\n  const PROD_WEIGHTS = [0.50, 0.30, 0.20];\n\n  const CHANNELS    = [\"[REPLACE_CHANNEL_1]\", \"[REPLACE_CHANNEL_2]\", \"[REPLACE_CHANNEL_3]\"];\n  const CHAN_WEIGHTS = [0.50, 0.35, 0.15];\n\n  const SEGMENTS    = [\"[REPLACE_SEGMENT_1]\", \"[REPLACE_SEGMENT_2]\", \"[REPLACE_SEGMENT_3]\"];\n  const SEG_WEIGHTS = [0.60, 0.30, 0.10];\n\n  // Failure reasons — customise to match the domain\n  const BIZ_DECLINE_REASONS = [\"INSUFFICIENT_FUNDS\", \"VALIDATION_FAILED\", \"LIMIT_EXCEEDED\", \"DO_NOT_HONOR\"];\n  const BIZ_DECLINE_WEIGHTS  = [0.35, 0.25, 0.25, 0.15];\n  const SYS_ERROR_REASONS    = [\"TIMEOUT\", \"SERVICE_UNAVAILABLE\", \"INTERNAL_ERROR\"];\n\n  // Platform/infrastructure alert types\n  const ALERT_TYPES    = [\"latency_spike\", \"error_rate_increase\", \"connection_pool\", \"memory_pressure\", \"queue_depth\", \"circuit_breaker\"];\n  const ALERT_WEIGHTS  = [0.28, 0.22, 0.18, 0.14, 0.10, 0.08];\n  const SEVERITIES     = [\"critical\", \"high\", \"medium\", \"low\"];\n  const SEV_WEIGHTS    = [0.05, 0.15, 0.40, 0.40];\n\n  // Service components (4–5 per transaction, models blast-radius risk)\n  const COMPONENTS = [\"api_gateway\", \"auth_service\", \"core_processor\", \"data_store\", \"downstream_connector\"];\n\n  // ─── DIURNAL MODEL ───────────────────────────────────────────────────────\n  // Returns a 0.0–1.0 volume multiplier for a given local hour.\n  // Shape: low overnight, ramp 07–09, peak 10–17, taper 18–22.\n  function diurnalMultiplier(utcH, isWeekend) {\n    const localH = ((utcH + TIMEZONE_OFFSET_HOURS) % 24 + 24) % 24;\n    const CURVE = [\n      0.25, 0.20, 0.18, 0.20,   // 00–03\n      0.28, 0.38, 0.55, 0.70,   // 04–07\n      0.82, 0.90, 0.95, 0.98,   // 08–11\n      1.00, 1.00, 0.98, 0.95,   // 12–15  ← peak\n      0.90, 0.82, 0.70, 0.60,   // 16–19\n      0.50, 0.42, 0.35, 0.28    // 20–23\n    ];\n    const base = CURVE[Math.max(0, Math.min(23, localH))];\n    return isWeekend ? base * 0.65 : base;\n  }\n\n  // ─── GENERIC HELPERS ─────────────────────────────────────────────────────\n  function nowUtc()   { return new Date(); }\n  function toIso(d)   { return new Date(d).toISOString(); }\n  function clampFuture(ts, now, safetyS) {\n    const max = new Date(now.getTime() - safetyS * 1000);\n    return ts > max ? max : ts;\n  }\n  function randInt(min, max)   { return Math.floor(Math.random() * (max - min + 1)) + min; }\n  function randFloat(min, max) { return Math.random() * (max - min) + min; }\n  function choose(arr)         { return arr[Math.floor(Math.random() * arr.length)]; }\n  function chooseWeighted(opts, wts) {\n    const total = wts.reduce((a, b) => a + b, 0);\n    const w = wts.map(v => v / (total || 1));\n    const r = Math.random();\n    let acc = 0;\n    for (let i = 0; i < opts.length; i++) { acc += w[i]; if (r <= acc) return opts[i]; }\n    return opts[opts.length - 1];\n  }\n  // Spreads `count` timestamps evenly across [start,end] with ±jitter fraction\n  function distribute(start, end, count, jitter) {\n    const spanMs = end.getTime() - start.getTime();\n    const stepMs = Math.max(1, Math.floor(spanMs / Math.max(1, count)));\n    const out = [];\n    for (let i = 0; i < count; i++) {\n      const base = new Date(start.getTime() + i * stepMs);\n      const jms  = Math.floor((Math.random() * 2 * jitter - jitter) * stepMs);\n      out.push(new Date(base.getTime() + jms));\n    }\n    return out;\n  }\n  function makeEvent(provider, etype, ts, extra, now) {\n    const safeTs = clampFuture(ts, now, 30);\n    const ev = { \"event.provider\": provider, \"event.type\": etype, \"timestamp\": toIso(safeTs) };\n    if (extra && typeof extra === \"object\") Object.assign(ev, extra);\n    return ev;\n  }\n  function countBy(arr, fn) {\n    const m = {};\n    for (const x of arr) { const k = fn(x); m[k] = (m[k] || 0) + 1; }\n    return m;\n  }\n  function afterMs(dt, ms) { return new Date(dt.getTime() + ms); }\n  function randomId(prefix, len) {\n    const hex = \"abcdef0123456789\";\n    let s = \"\";\n    for (let i = 0; i < len; i++) s += hex[Math.floor(Math.random() * hex.length)];\n    return prefix + s.toUpperCase();\n  }\n\n  // ─── TIME CONTEXT ────────────────────────────────────────────────────────\n  const now      = nowUtc();\n  const start    = new Date(now.getTime() - HOURS_WINDOW * 3600000);\n  const utcH     = now.getUTCHours();\n  const utcDay   = now.getUTCDay();\n  const isWeekend = utcDay === 0 || utcDay === 6;\n  const dayNames  = [\"sunday\",\"monday\",\"tuesday\",\"wednesday\",\"thursday\",\"friday\",\"saturday\"];\n  const dayName   = dayNames[utcDay];\n  const DIURNAL   = diurnalMultiplier(utcH, isWeekend);\n\n  // Latency increases at peak load (queuing effect)\n  const loadFactor = DIURNAL > 0.90 ? 1.20 : (DIURNAL > 0.75 ? 1.08 : 1.0);\n  // Overnight: slightly higher failure rate (fewer support staff)\n  const effectiveDeclineRate = DECLINE_RATE * (utcH >= 22 || utcH < 6 ? 1.5 : 1.0);\n\n  // Scale all counts by diurnal multiplier\n  const TXN_COUNT   = Math.max(10, Math.round(randInt(TXN_MIN, TXN_MAX) * DIURNAL));\n  const ORDER_COUNT = Math.max(2,  Math.round(randInt(ORDER_MIN, ORDER_MAX) * DIURNAL));\n  const ALERT_COUNT = Math.max(1,  Math.round(randInt(ALERT_MIN, ALERT_MAX) * (0.40 + DIURNAL * 0.65)));\n\n  const events = [];\n\n  // ─── SECTION 1: Primary Transactions ─────────────────────────────────────\n  // [REPLACE] Rename event types to match the customer domain, e.g.:\n  //   \"payment.authorization.completed\", \"order.placed\", \"booking.confirmed\"\n  const txnTimes = distribute(afterMs(start, 60000), afterMs(now, -60000), TXN_COUNT, 0.20);\n\n  for (let i = 0; i < txnTimes.length; i++) {\n    const ts      = txnTimes[i];\n    const envIdx  = chooseWeighted([0, 1], ENV_WEIGHTS);\n    const env     = ENVIRONMENTS[envIdx];\n    const product = chooseWeighted(PRODUCTS, PROD_WEIGHTS);\n    const channel = chooseWeighted(CHANNELS, CHAN_WEIGHTS);\n    const segment = chooseWeighted(SEGMENTS, SEG_WEIGHTS);\n    const amount  = Number(randFloat(10, 5000).toFixed(2)); // [REPLACE] range\n\n    const isSysErr  = Math.random() < ERROR_RATE;\n    const isBizDecl = !isSysErr && Math.random() < effectiveDeclineRate;\n    const isFailed  = isSysErr || isBizDecl;\n    const latency   = Math.round(randFloat(50, 300) * loadFactor * (isFailed ? 4 : 1));\n\n    const extra = {\n      \"transaction.id\":          randomId(\"TXN-\", 10),\n      \"customer.id\":             randomId(\"CUST-\", 8),\n      \"product\":                 product,\n      \"channel\":                 channel,\n      \"customer.segment\":        segment,\n      \"transaction.amount\":      amount,\n      \"currency\":                \"USD\", // [REPLACE]\n      \"response.time.ms\":        latency,\n      \"environment\":             env.name,\n      \"processing.location\":     env.location,\n      \"geo.location.latitude\":   env.lat,\n      \"geo.location.longitude\":  env.lon,\n      \"hour.of.day\":             utcH,\n      \"day.of.week\":             dayName,\n      \"is.weekend\":              isWeekend,\n      \"diurnal.multiplier\":      Math.round(DIURNAL * 100) / 100\n    };\n    if (isFailed) {\n      extra[\"failure.reason\"]   = isSysErr\n        ? choose(SYS_ERROR_REASONS)\n        : chooseWeighted(BIZ_DECLINE_REASONS, BIZ_DECLINE_WEIGHTS);\n      extra[\"failure.category\"] = isSysErr ? \"system\" : \"business\";\n    }\n\n    // [REPLACE] event type names\n    const etype = isFailed ? \"transaction.failed\" : \"transaction.completed\";\n    events.push(makeEvent(EVENT_PROVIDER, etype, ts, extra, now));\n  }\n\n  // ─── SECTION 2: Secondary Business Events ────────────────────────────────\n  // [REPLACE] This section models a secondary flow (e.g. account opens,\n  //   bookings, subscriptions, card issuance). Rename fields accordingly.\n  const orderTimes = distribute(afterMs(start, 180000), afterMs(now, -180000), ORDER_COUNT, 0.15);\n\n  for (let i = 0; i < orderTimes.length; i++) {\n    const ts      = orderTimes[i];\n    const envIdx  = chooseWeighted([0, 1], ENV_WEIGHTS);\n    const env     = ENVIRONMENTS[envIdx];\n    const product = chooseWeighted(PRODUCTS, PROD_WEIGHTS);\n    const channel = chooseWeighted(CHANNELS, CHAN_WEIGHTS);\n    const segment = chooseWeighted(SEGMENTS, SEG_WEIGHTS);\n\n    events.push(makeEvent(EVENT_PROVIDER, \"secondary.event.completed\", ts, { // [REPLACE] event type\n      \"event.id\":                randomId(\"EVT-\", 8),\n      \"customer.id\":             randomId(\"CUST-\", 8),\n      \"product\":                 product,\n      \"channel\":                 channel,\n      \"customer.segment\":        segment,\n      \"environment\":             env.name,\n      \"processing.location\":     env.location,\n      \"geo.location.latitude\":   env.lat,\n      \"geo.location.longitude\":  env.lon,\n      \"hour.of.day\":             utcH,\n      \"day.of.week\":             dayName,\n      \"is.weekend\":              isWeekend\n    }, now));\n  }\n\n  // ─── SECTION 3: Platform / Infrastructure Alerts ─────────────────────────\n  // Models operational noise (alert fatigue use case).\n  // ALERT_COUNT scales with DIURNAL so peak hours show more alerts.\n  const alertTimes = distribute(afterMs(start, 60000), afterMs(now, -60000), ALERT_COUNT, 0.12);\n\n  for (let i = 0; i < alertTimes.length; i++) {\n    const ts        = alertTimes[i];\n    const envIdx    = chooseWeighted([0, 1], ENV_WEIGHTS);\n    const env       = ENVIRONMENTS[envIdx];\n    const alertType = chooseWeighted(ALERT_TYPES, ALERT_WEIGHTS);\n    const severity  = chooseWeighted(SEVERITIES, SEV_WEIGHTS);\n    const component = choose(COMPONENTS);\n    const resMins   = severity === \"critical\" ? randInt(5, 30) : (severity === \"high\" ? randInt(10, 60) : randInt(15, 120));\n    const autoResolved = (severity === \"low\" || severity === \"medium\") ? Math.random() > 0.3 : Math.random() > 0.7;\n\n    events.push(makeEvent(EVENT_PROVIDER, \"platform.alert.raised\", ts, {\n      \"alert.id\":                randomId(\"ALT-\", 8),\n      \"alert.type\":              alertType,\n      \"severity\":                severity,\n      \"component\":               component,\n      \"environment\":             env.name,\n      \"processing.location\":     env.location,\n      \"resolution.time.minutes\": resMins,\n      \"auto.resolved\":           autoResolved,\n      \"geo.location.latitude\":   env.lat,\n      \"geo.location.longitude\":  env.lon,\n      \"hour.of.day\":             utcH,\n      \"day.of.week\":             dayName,\n      \"is.weekend\":              isWeekend\n    }, now));\n  }\n\n  // ─── ADD SECTIONS 4, 5 … as needed ───────────────────────────────────────\n  // Copy the pattern from sections 1–3 above. Common additions:\n  //   Section 4: Fraud / risk alerts\n  //   Section 5: Customer satisfaction / NPS surveys\n  //   Section 6: Batch job completions (settlement, reporting)\n  //   Section 7: User session / engagement events\n\n  // ─── INGEST ──────────────────────────────────────────────────────────────\n  const totals = countBy(events, e => e[\"event.type\"]);\n  const batches = [];\n\n  for (let i = 0; i < events.length; i += CHUNK) {\n    const batch = events.slice(i, i + CHUNK);\n    const res = await fetch(\"/platform/classic/environment-api/v2/bizevents/ingest\", {\n      method: \"POST\",\n      headers: { \"Content-Type\": \"application/json\" },\n      body: JSON.stringify(batch)\n    });\n\n    let text = \"\";\n    try { text = await res.text(); } catch (_) {}\n\n    if (!res.ok) {\n      console.error(`Ingest failed batch ${i}–${i + batch.length - 1}: HTTP ${res.status} ${text}`);\n      throw new Error(`BizEvents ingest failed: HTTP ${res.status}`);\n    }\n    batches.push({ range: `${i}–${i + batch.length - 1}`, status: res.status });\n  }\n\n  return {\n    client:    CLIENT_NAME,\n    totals,\n    batches,\n    sample:    events.slice(0, 2),\n    meta: {\n      totalEvents:        events.length,\n      utcHour:            utcH,\n      dayName,\n      isWeekend,\n      diurnalMultiplier:  Math.round(DIURNAL * 100) / 100,\n      loadFactor,\n      transactions:       TXN_COUNT,\n      secondaryEvents:    ORDER_COUNT,\n      platformAlerts:     ALERT_COUNT\n    }\n  };\n}"
      },
      "action": "dynatrace.automations:run-javascript",
      "position": {
        "x": 0,
        "y": 1
      },
      "description": "Hourly BizEvent injector for [REPLACE_CLIENT_NAME] demo. Generates realistic business events with diurnal traffic shaping (volume scales by UTC hour). Replace all [REPLACE_...] tokens before use. Sections: (1) Primary transactions, (2) Secondary business events, (3) Platform/infrastructure alerts.",
      "predecessors": []
    }
  },
  "description": "Template: hourly BizEvent injector with diurnal traffic model. Replace [REPLACE_...] tokens with customer-specific values before importing.",
  "ownerType": "USER",
  "isPrivate": true,
  "trigger": {
    "schedule": {
      "isActive": true,
      "isFaulty": false,
      "trigger": {
        "type": "interval",
        "intervalMinutes": 60
      },
      "rule": null,
      "filterParameters": {
        "earliestStart": "2026-01-01",
        "earliestStartTime": "00:00"
      },
      "timezone": "UTC",
      "inputs": {}
    }
  },
  "schemaVersion": 3,
  "result": null,
  "input": {},
  "hourlyExecutionLimit": 1000,
  "type": "STANDARD",
  "guide": null
}